Metadata-Version: 2.1
Name: zheinit
Version: 0.0.98
Summary: Init zhei environment.
Home-page: https://github.com/deng1fan
Author: deng1fan
Author-email: dengyifan@iie.ac.cn
Requires-Python: >=3.6
